CHANGELOG.md
LICENSE
MANIFEST.in
README.md
pypi_desc.md
setup.cfg
setup.py
gne/__init__.py
gne/defaults.py
gne/exceptions.py
gne/utils.py
gne.egg-info/PKG-INFO
gne.egg-info/SOURCES.txt
gne.egg-info/dependency_links.txt
gne.egg-info/requires.txt
gne.egg-info/top_level.txt
gne/extractor/AuthorExtractor.py
gne/extractor/ContentExtractor.py
gne/extractor/ListExtractor.py
gne/extractor/MetaExtractor.py
gne/extractor/TimeExtractor.py
gne/extractor/TitleExtractor.py
gne/extractor/__init__.py